pwngrid_api/__init__.py
pwngrid_api/pwngrid_api.py
pwngrid_api/utils.py
pwngrid_api-0.0.1.dist-info/LICENSE
pwngrid_api-0.0.1.dist-info/METADATA
pwngrid_api-0.0.1.dist-info/WHEEL
pwngrid_api-0.0.1.dist-info/top_level.txt
pwngrid_api-0.0.1.dist-info/RECORD
