Metadata-Version: 2.1
Name: pwngrid-api
Version: 0.0.1
Summary: Pwnagotchi's Pwngrid API client
Home-page: https://github.com/python273/pwngrid-api
Author: python273
Author-email: pwngrid@python273.pw
License: MIT
Download-URL: https://github.com/python273/pwngrid-api/archive/v0.0.1.zip
Platform: UNKNOWN
Classifier: License :: OSI Approved :: MIT License
Classifier: Operating System :: OS Independent
Classifier: Programming Language :: Python
Classifier: Programming Language :: Python :: 3
Classifier: Programming Language :: Python :: 3.4
Classifier: Programming Language :: Python :: 3.5
Classifier: Programming Language :: Python :: 3.6
Classifier: Programming Language :: Python :: 3.7
Classifier: Programming Language :: Python :: 3.8
Classifier: Programming Language :: Python :: Implementation :: PyPy
Classifier: Programming Language :: Python :: Implementation :: CPython
Requires-Dist: requests
Requires-Dist: cryptography
